speechcolab/__init__.py
speechcolab/datasets/__init__.py
speechcolab/datasets/gigaspeech.py
speechcolab/utils/__init__.py
speechcolab/utils/download.py
test/__init__.py
test/test_common.py
test/datasets/__init__.py
test/datasets/test_gigaspeech.py
test/utils/__init__.py
test/utils/test_download.py
speechcolab-0.0.6a0.dist-info/LICENSE
speechcolab-0.0.6a0.dist-info/METADATA
speechcolab-0.0.6a0.dist-info/WHEEL
speechcolab-0.0.6a0.dist-info/top_level.txt
speechcolab-0.0.6a0.dist-info/RECORD
